ssh2http/__init__.py
ssh2http/__main__.py
ssh2http/client.py
ssh2http-0.1.0.dist-info/METADATA
ssh2http-0.1.0.dist-info/WHEEL
ssh2http-0.1.0.dist-info/top_level.txt
ssh2http-0.1.0.dist-info/RECORD
