Metadata-Version: 2.1
Name: ssh2http
Version: 0.1.0
Summary: Simple utility to tunnel ssh over http
Home-page: https://github.com/4thel00z/ssh2http
Author: 4thel00z
Author-email: 4thel00z@gmail.com
License: GPL
Platform: UNKNOWN
Classifier: Programming Language :: Python
Classifier: Programming Language :: Python :: 3.7
Classifier: Programming Language :: Python :: 3.8
Classifier: Programming Language :: Python :: 3.9
Requires-Python: >=3.6
Requires-Dist: pwntools (==4.3.1)
Requires-Dist: sanic (==20.12.2)
